PyPl8/ProcessImages.py
PyPl8/__init__.py
PyPl8/Barcodes/BarcodeMethods.py
PyPl8/Barcodes/__init__.py
PyPl8/Data/Im1.jpg
PyPl8/Data/Im2.JPG
PyPl8/Data/Im3.jpg
PyPl8/Data/__init__.py
PyPl8/Preprocessing/PreprocessingMethods.py
PyPl8/Preprocessing/__init__.py
PyPl8-1.0.8.dist-info/LICENSE
PyPl8-1.0.8.dist-info/METADATA
PyPl8-1.0.8.dist-info/WHEEL
PyPl8-1.0.8.dist-info/top_level.txt
PyPl8-1.0.8.dist-info/RECORD
