Metadata-Version: 2.1
Name: PyPl8
Version: 1.0.8
Home-page: https://github.com/lacyk3/PyPl8
Author: Katherine Owens
Author-email: kowens@pnri.org
Project-URL: Bug Tracker, https://github.com/lacyk3/PyPl8/issues
Classifier: Programming Language :: Python :: 3
Classifier: License :: OSI Approved :: GNU General Public License v2 (GPLv2)
License-File: LICENSE
Requires-Dist: numpy
Requires-Dist: pandas
Requires-Dist: scipy
Requires-Dist: matplotlib
Requires-Dist: scikit-image
Requires-Dist: opencv-python
Requires-Dist: openpyxl
Requires-Dist: pyzbar
Requires-Dist: Ipython
